monday_helper/__init__.py
monday_helper/graphql_queries.py
monday_helper/monday_api_client.py
monday_helpers/__init__.py
monday_helpers/graphql_queries.py
monday_helpers/monday_api_client.py
monday_helper-1.0.1.dist-info/LICENSE.TXT
monday_helper-1.0.1.dist-info/METADATA
monday_helper-1.0.1.dist-info/WHEEL
monday_helper-1.0.1.dist-info/top_level.txt
monday_helper-1.0.1.dist-info/RECORD
