Metadata-Version: 2.1
Name: monday_helper
Version: 1.0.1
Summary: Monday API
Author: white_hat25
Author-email: devmarcel30@gmail.com
License-File: LICENSE.TXT
Requires-Dist: requests
